jtools/__init__.py
jtools/_cli.py
jtools/utils.py
jtools/align/__init__.py
jtools/align/filter_qname.py
jtools/data/__init__.py
jtools/data/organize.py
jtools/fastx/__init__.py
jtools/fastx/fastq_info.py
jtools/interval/__init__.py
jtools/interval/multijaccard.py
bio_jtools-0.2.3.dist-info/LICENSE
bio_jtools-0.2.3.dist-info/METADATA
bio_jtools-0.2.3.dist-info/WHEEL
bio_jtools-0.2.3.dist-info/entry_points.txt
bio_jtools-0.2.3.dist-info/top_level.txt
bio_jtools-0.2.3.dist-info/zip-safe
bio_jtools-0.2.3.dist-info/RECORD
