Metadata-Version: 2.1
Name: bio-jtools
Version: 0.2.3
Summary: Various bioinformatics tools in one package
Home-page: http://github.com/jrhawley/bio-jtools
Author: James Hawley
Author-email: james.hawley@mail.utoronto.ca
License: UNKNOWN
Platform: UNKNOWN
Classifier: Intended Audience :: Science/Research
Classifier: License :: OSI Approved :: GNU General Public License v3 (GPLv3)
Classifier: Operating System :: OS Independent
Classifier: Programming Language :: Python
Classifier: Programming Language :: Python :: 3
Classifier: Programming Language :: Python :: 3.6
Classifier: Programming Language :: Python :: 3.7
Classifier: Topic :: Scientific/Engineering
Classifier: Topic :: Scientific/Engineering :: Bio-Informatics
Classifier: Topic :: Software Development :: Libraries :: Python Modules
Classifier: Natural Language :: English
Requires-Dist: numpy (>=1.11)
Requires-Dist: pandas (>=0.15.0)
Requires-Dist: pybedtools
Requires-Dist: biopython
Requires-Dist: seaborn
Requires-Dist: tqdm
